{"id":801,"list":[{"code":111,"indent":0,"parameters":[12,"$gameParty._commonEventNum[\"story_021_map124_001\"] > 1"]},{"code":101,"indent":1,"parameters":["Actor0124",0,2,2,""]},{"code":401,"indent":1,"parameters":["..."]},{"code":101,"indent":1,"parameters":["Actor0124",0,2,2,""]},{"code":401,"indent":1,"parameters":["What are you going to do now?"]},{"code":401,"indent":1,"parameters":[""]},{"code":101,"indent":1,"parameters":["Actor0001",0,0,2,""]},{"code":401,"indent":1,"parameters":["Me?\\."]},{"code":401,"indent":1,"parameters":["Good question."]},{"code":101,"indent":1,"parameters":["Actor0001",4,0,2,""]},{"code":401,"indent":1,"parameters":["I don't have a plan."]},{"code":101,"indent":1,"parameters":["Actor0124",0,2,2,""]},{"code":401,"indent":1,"parameters":["..."]},{"code":101,"indent":1,"parameters":["Actor0001",1,0,2,""]},{"code":401,"indent":1,"parameters":["You have any good jobs?"]},{"code":101,"indent":1,"parameters":["Actor0124",0,2,2,""]},{"code":401,"indent":1,"parameters":["..."]},{"code":101,"indent":1,"parameters":["Actor0124",0,2,2,""]},{"code":401,"indent":1,"parameters":["No."]},{"code":101,"indent":1,"parameters":["Actor0001",4,0,2,""]},{"code":401,"indent":1,"parameters":["I didn't think so."]},{"code":0,"indent":1,"parameters":[]},{"code":412,"indent":0,"parameters":[]},{"code":111,"indent":0,"parameters":[12,"$gameParty._commonEventNum[\"story_021_map124_001\"] == 1"]},{"code":101,"indent":1,"parameters":["Actor0124",0,2,2,""]},{"code":401,"indent":1,"parameters":["..."]},{"code":101,"indent":1,"parameters":["Actor0124",0,2,2,""]},{"code":401,"indent":1,"parameters":["It's you."]},{"code":101,"indent":1,"parameters":["Actor0001",0,0,2,""]},{"code":401,"indent":1,"parameters":["You're still here."]},{"code":401,"indent":1,"parameters":[""]},{"code":101,"indent":1,"parameters":["Actor0124",0,2,2,""]},{"code":401,"indent":1,"parameters":["It's a good place to find jobs."]},{"code":101,"indent":1,"parameters":["Actor0001",0,0,2,""]},{"code":401,"indent":1,"parameters":["Yeah,\\. that's pretty important."]},{"code":401,"indent":1,"parameters":[""]},{"code":0,"indent":1,"parameters":[]},{"code":412,"indent":0,"parameters":[]},{"code":118,"indent":0,"parameters":["End"]},{"code":357,"indent":0,"parameters":["Plugin_EventCommand","exit","exit",{}]},{"code":0,"indent":0,"parameters":[]}],"name":"story_021_map124_001","switchId":1,"trigger":0}