{"id":687,"list":[{"code":101,"indent":0,"parameters":["Actor0052",0,2,2,""]},{"code":401,"indent":0,"parameters":["Nobody was hurt seriously"]},{"code":401,"indent":0,"parameters":["in the expedition."]},{"code":101,"indent":0,"parameters":["Actor0052",0,2,2,""]},{"code":401,"indent":0,"parameters":["There are still monsters\\."]},{"code":401,"indent":0,"parameters":["in the world."]},{"code":118,"indent":0,"parameters":["End"]},{"code":357,"indent":0,"parameters":["Plugin_EventCommand","exit","exit",{}]},{"code":0,"indent":0,"parameters":[]}],"name":"story_016_map52_001","switchId":1,"trigger":0}