{"id":832,"list":[{"code":230,"indent":0,"parameters":[60]},{"code":108,"indent":0,"parameters":["データ設定"]},{"code":108,"indent":0,"parameters":["仲間加入変更"]},{"code":108,"indent":0,"parameters":["BGM設定"]},{"code":221,"indent":0,"parameters":[]},{"code":108,"indent":0,"parameters":["背景設定"]},{"code":283,"indent":0,"parameters":["School",""]},{"code":355,"indent":0,"parameters":["BackGroundManager.resetPosition();"]},{"code":355,"indent":0,"parameters":["// 背景の移動(秒,x,y,repeat)"]},{"code":655,"indent":0,"parameters":["BackGroundManager.moveUV(0,0,0,false);"]},{"code":355,"indent":0,"parameters":["// 天気設定（前面）"]},{"code":655,"indent":0,"parameters":["EventManager.clearWeather();"]},{"code":655,"indent":0,"parameters":["BackGroundManager.clearWeather();"]},{"code":108,"indent":0,"parameters":["ピクチャ設定"]},{"code":357,"indent":0,"parameters":["Plugin_EventCommand","setBattlePicture","setBattlePicture",{"label":"School6","x":"480","y":"288","opacity":"0"}]},{"code":657,"indent":0,"parameters":["label = School6"]},{"code":657,"indent":0,"parameters":["x = 480"]},{"code":657,"indent":0,"parameters":["y = 288"]},{"code":657,"indent":0,"parameters":["opacity = 0"]},{"code":118,"indent":0,"parameters":["School6"]},{"code":231,"indent":0,"parameters":[1,"Actor0034",0,0,120,320,100,100,0,0]},{"code":231,"indent":0,"parameters":[1,"Actor0035",0,0,840,320,100,100,0,0]},{"code":231,"indent":0,"parameters":[1,"white",0,0,480,480,2000,2000,0,0]},{"code":222,"indent":0,"parameters":[]},{"code":230,"indent":0,"parameters":[60]},{"code":101,"indent":0,"parameters":["Actor0004",5,0,2,""]},{"code":401,"indent":0,"parameters":["(*sigh*\\."]},{"code":401,"indent":0,"parameters":["Regular class is boring.)"]},{"code":230,"indent":0,"parameters":[60]},{"code":101,"indent":0,"parameters":["Actor0004",0,0,2,""]},{"code":401,"indent":0,"parameters":["Class is out now.\\. I guess I'll go home."]},{"code":357,"indent":0,"parameters":["Plugin_EventCommand","moveActors","moveActors",{"direction":"4"}]},{"code":657,"indent":0,"parameters":["direction = 4"]},{"code":118,"indent":0,"parameters":["School6"]},{"code":232,"indent":0,"parameters":[1,0,0,0,0,0,100,100,255,0,30,false,0]},{"code":230,"indent":0,"parameters":[120]},{"code":357,"indent":0,"parameters":["Plugin_EventCommand","moveActors","moveActors",{"direction":"8"}]},{"code":657,"indent":0,"parameters":["direction = 8"]},{"code":230,"indent":0,"parameters":[60]},{"code":118,"indent":0,"parameters":["Actor0034"]},{"code":232,"indent":0,"parameters":[1,0,0,0,120,0,100,100,255,0,30,false,0]},{"code":118,"indent":0,"parameters":["Actor0035"]},{"code":232,"indent":0,"parameters":[1,0,0,0,-120,0,100,100,255,0,30,false,0]},{"code":230,"indent":0,"parameters":[120]},{"code":101,"indent":0,"parameters":["Actor0004",5,0,2,""]},{"code":401,"indent":0,"parameters":["What?\\."]},{"code":401,"indent":0,"parameters":["You're in my way."]},{"code":101,"indent":0,"parameters":["Actor0034",0,2,2,""]},{"code":401,"indent":0,"parameters":["I heard they made you quit\\."]},{"code":401,"indent":0,"parameters":["your magic research."]},{"code":101,"indent":0,"parameters":["Actor0035",0,2,2,""]},{"code":401,"indent":0,"parameters":["I mean, of course they did."]},{"code":101,"indent":0,"parameters":["Actor0035",0,2,2,""]},{"code":401,"indent":0,"parameters":["Magic can only cause harm."]},{"code":101,"indent":0,"parameters":["Actor0004",5,0,2,""]},{"code":401,"indent":0,"parameters":["..."]},{"code":357,"indent":0,"parameters":["Plugin_EventCommand","moveActors","moveActors",{"direction":"8"}]},{"code":657,"indent":0,"parameters":["direction = 8"]},{"code":118,"indent":0,"parameters":["Actor0034"]},{"code":232,"indent":0,"parameters":[1,0,0,0,0,-40,100,100,255,0,8,true,0]},{"code":250,"indent":0,"parameters":[{"name":"Blow9","volume":90,"pitch":100,"pan":0}]},{"code":232,"indent":0,"parameters":[1,0,0,0,0,40,100,100,255,0,8,false,0]},{"code":224,"indent":0,"parameters":[[255,255,255,170],30,false]},{"code":225,"indent":0,"parameters":[2,2,30,false]},{"code":230,"indent":0,"parameters":[60]},{"code":101,"indent":0,"parameters":["Actor0004",2,0,2,""]},{"code":401,"indent":0,"parameters":["Ow!\\."]},{"code":401,"indent":0,"parameters":["What did you do that for?!"]},{"code":101,"indent":0,"parameters":["Actor0034",0,2,2,""]},{"code":401,"indent":0,"parameters":["Don't get carried away.\\."]},{"code":401,"indent":0,"parameters":["Check your pompous attitude."]},{"code":101,"indent":0,"parameters":["Actor0004",6,0,2,""]},{"code":401,"indent":0,"parameters":["What?!"]},{"code":101,"indent":0,"parameters":["Actor0035",0,2,2,""]},{"code":401,"indent":0,"parameters":["You can't do anything\\."]},{"code":401,"indent":0,"parameters":["without your older sister."]},{"code":101,"indent":0,"parameters":["Actor0004",5,0,2,""]},{"code":401,"indent":0,"parameters":["What's she have to do with anything?"]},{"code":118,"indent":0,"parameters":["Actor0035"]},{"code":232,"indent":0,"parameters":[1,0,0,0,0,-40,100,100,255,0,8,true,0]},{"code":250,"indent":0,"parameters":[{"name":"Blow9","volume":90,"pitch":100,"pan":0}]},{"code":232,"indent":0,"parameters":[1,0,0,0,0,40,100,100,255,0,8,true,0]},{"code":224,"indent":0,"parameters":[[255,255,255,170],30,false]},{"code":225,"indent":0,"parameters":[1,1,30,true]},{"code":230,"indent":0,"parameters":[90]},{"code":101,"indent":0,"parameters":["Actor0004",2,0,2,""]},{"code":401,"indent":0,"parameters":["Is violence fun?"]},{"code":401,"indent":0,"parameters":[""]},{"code":101,"indent":0,"parameters":["Actor0004",6,0,2,""]},{"code":401,"indent":0,"parameters":["Does it feel good to hit someone\\."]},{"code":401,"indent":0,"parameters":["better than you?"]},{"code":101,"indent":0,"parameters":["Actor0034",0,2,2,""]},{"code":401,"indent":0,"parameters":["You little!"]},{"code":118,"indent":0,"parameters":["Actor0034"]},{"code":232,"indent":0,"parameters":[1,0,0,0,0,-40,100,100,255,0,8,true,0]},{"code":250,"indent":0,"parameters":[{"name":"Blow9","volume":90,"pitch":100,"pan":0}]},{"code":232,"indent":0,"parameters":[1,0,0,0,0,40,100,100,255,0,8,false,0]},{"code":225,"indent":0,"parameters":[1,1,30,false]},{"code":118,"indent":0,"parameters":["white"]},{"code":232,"indent":0,"parameters":[1,0,0,0,0,0,100,100,255,0,1,true,0]},{"code":224,"indent":0,"parameters":[[255,0,0,170],30,false]},{"code":230,"indent":0,"parameters":[30]},{"code":221,"indent":0,"parameters":[]},{"code":250,"indent":0,"parameters":[{"name":"Blow7","volume":90,"pitch":100,"pan":0}]},{"code":224,"indent":0,"parameters":[[255,0,0,170],30,false]},{"code":230,"indent":0,"parameters":[60]},{"code":250,"indent":0,"parameters":[{"name":"Blow8","volume":90,"pitch":100,"pan":0}]},{"code":224,"indent":0,"parameters":[[255,0,0,170],30,false]},{"code":230,"indent":0,"parameters":[48]},{"code":250,"indent":0,"parameters":[{"name":"Blow9","volume":90,"pitch":100,"pan":0}]},{"code":224,"indent":0,"parameters":[[255,0,0,170],30,false]},{"code":230,"indent":0,"parameters":[30]},{"code":250,"indent":0,"parameters":[{"name":"Blow4","volume":90,"pitch":100,"pan":0}]},{"code":224,"indent":0,"parameters":[[255,0,0,170],30,false]},{"code":230,"indent":0,"parameters":[90]},{"code":101,"indent":0,"parameters":["Actor0034",0,2,2,""]},{"code":401,"indent":0,"parameters":["It's hilarious.\\."]},{"code":401,"indent":0,"parameters":["Even the teachers ignore us."]},{"code":101,"indent":0,"parameters":["Actor0034",0,2,2,""]},{"code":401,"indent":0,"parameters":["They must\\. really hate you."]},{"code":101,"indent":0,"parameters":["Actor0035",0,2,2,""]},{"code":401,"indent":0,"parameters":["Your student president of an older sister"]},{"code":401,"indent":0,"parameters":["graduated,\\. and isn't here anymore."]},{"code":101,"indent":0,"parameters":["Actor0035",0,2,2,""]},{"code":401,"indent":0,"parameters":["There's nobody here to protect you now."]},{"code":230,"indent":0,"parameters":[60]},{"code":118,"indent":0,"parameters":["End"]},{"code":221,"indent":0,"parameters":[]},{"code":357,"indent":0,"parameters":["Plugin_EventCommand","clearPictures","clearPictures",{}]},{"code":222,"indent":0,"parameters":[]},{"code":357,"indent":0,"parameters":["Plugin_EventCommand","exit","exit",{}]},{"code":0,"indent":0,"parameters":[]}],"name":"word_004_002","switchId":1,"trigger":0}