{"id":130,"list":[{"code":108,"indent":0,"parameters":["データ設定"]},{"code":122,"indent":0,"parameters":[47,47,0,0,60]},{"code":121,"indent":0,"parameters":[301,301,1]},{"code":121,"indent":0,"parameters":[262,262,1]},{"code":121,"indent":0,"parameters":[302,302,0]},{"code":108,"indent":0,"parameters":["仲間加入変更"]},{"code":129,"indent":0,"parameters":[2,0,false]},{"code":108,"indent":0,"parameters":["BGM設定"]},{"code":108,"indent":0,"parameters":["背景設定"]},{"code":108,"indent":0,"parameters":["ピクチャ設定"]},{"code":231,"indent":0,"parameters":[1,"Actor0002",1,0,480,720,100,100,0,0]},{"code":231,"indent":0,"parameters":[1,"Actor0043",1,0,1280,720,-100,100,0,0]},{"code":357,"indent":0,"parameters":["Plugin_VoiceCommand","playVoiceActor2","playVoiceActor2",{"voiceId":"5"}]},{"code":657,"indent":0,"parameters":["voiceId = 5"]},{"code":101,"indent":0,"parameters":["Actor0002",6,2,2]},{"code":401,"indent":0,"parameters":["\\N[5]！"]},{"code":250,"indent":0,"parameters":[{"name":"Foot1","volume":90,"pitch":110,"pan":0}]},{"code":230,"indent":0,"parameters":[12]},{"code":250,"indent":0,"parameters":[{"name":"Foot1","volume":90,"pitch":110,"pan":0}]},{"code":230,"indent":0,"parameters":[12]},{"code":250,"indent":0,"parameters":[{"name":"Foot1","volume":90,"pitch":110,"pan":0}]},{"code":230,"indent":0,"parameters":[12]},{"code":250,"indent":0,"parameters":[{"name":"Foot1","volume":90,"pitch":110,"pan":0}]},{"code":230,"indent":0,"parameters":[12]},{"code":230,"indent":0,"parameters":[60]},{"code":357,"indent":0,"parameters":["Plugin_EventCommand","moveActors","moveActors",{"direction":"6"}]},{"code":657,"indent":0,"parameters":["direction = 6"]},{"code":230,"indent":0,"parameters":[60]},{"code":118,"indent":0,"parameters":["Actor0002"]},{"code":232,"indent":0,"parameters":[1,0,0,0,0,0,100,100,255,0,30,true,0]},{"code":213,"indent":0,"parameters":[-1,6,false]},{"code":357,"indent":0,"parameters":["Plugin_VoiceCommand","playVoiceActor5","playVoiceActor5",{"voiceId":"33"}]},{"code":657,"indent":0,"parameters":["voiceId = 33"]},{"code":101,"indent":0,"parameters":["Actor0005",6,0,2,""]},{"code":401,"indent":0,"parameters":["\\N[2]！？\\."]},{"code":401,"indent":0,"parameters":["どうしたの？\\. 仕事中じゃ？"]},{"code":118,"indent":0,"parameters":["Actor0002"]},{"code":101,"indent":0,"parameters":["Actor0002",6,2,2]},{"code":401,"indent":0,"parameters":["はぁ\\. はぁ\\."]},{"code":401,"indent":0,"parameters":["追い付いた"]},{"code":213,"indent":0,"parameters":[-1,11,false]},{"code":230,"indent":0,"parameters":[30]},{"code":357,"indent":0,"parameters":["Plugin_VoiceCommand","playVoiceActor2","playVoiceActor2",{"voiceId":"40"}]},{"code":657,"indent":0,"parameters":["voiceId = 40"]},{"code":101,"indent":0,"parameters":["Actor0002",0,2,2]},{"code":401,"indent":0,"parameters":["ごめんね\\."]},{"code":401,"indent":0,"parameters":["驚かせるつもりじゃなかったんだけど"]},{"code":357,"indent":0,"parameters":["Plugin_VoiceCommand","playVoiceActor2","playVoiceActor2",{"voiceId":"23"}]},{"code":657,"indent":0,"parameters":["voiceId = 23"]},{"code":101,"indent":0,"parameters":["Actor0002",0,2,2]},{"code":401,"indent":0,"parameters":["\\N[5]\\."]},{"code":401,"indent":0,"parameters":["いきなりお店にやってくるんだもん"]},{"code":357,"indent":0,"parameters":["Plugin_VoiceCommand","playVoiceActor5","playVoiceActor5",{"voiceId":"40"}]},{"code":657,"indent":0,"parameters":["voiceId = 40"]},{"code":101,"indent":0,"parameters":["Actor0005",0,0,2]},{"code":401,"indent":0,"parameters":["さっきは話の流れで…\\."]},{"code":401,"indent":0,"parameters":["ごめん"]},{"code":101,"indent":0,"parameters":["Actor0002",0,2,2]},{"code":401,"indent":0,"parameters":["別に気にしてないよ"]},{"code":357,"indent":0,"parameters":["Plugin_VoiceCommand","playVoiceActor2","playVoiceActor2",{"voiceId":"26"}]},{"code":657,"indent":0,"parameters":["voiceId = 26"]},{"code":101,"indent":0,"parameters":["Actor0002",8,2,2,""]},{"code":401,"indent":0,"parameters":["でも…\\."]},{"code":401,"indent":0,"parameters":["\\N[14]さんのこと"]},{"code":101,"indent":0,"parameters":["Actor0002",8,2,2,""]},{"code":401,"indent":0,"parameters":["また調べてるんだよね？"]},{"code":101,"indent":0,"parameters":["Actor0005",0,0,2]},{"code":401,"indent":0,"parameters":["…うん"]},{"code":118,"indent":0,"parameters":["Actor0002"]},{"code":213,"indent":0,"parameters":[-1,8,false]},{"code":357,"indent":0,"parameters":["Plugin_EventCommand","changeActorFace","changeActorFace",{"faceType":"5"}]},{"code":657,"indent":0,"parameters":["faceType = 5"]},{"code":230,"indent":0,"parameters":[90]},{"code":213,"indent":0,"parameters":[-1,11,false]},{"code":357,"indent":0,"parameters":["Plugin_VoiceCommand","playVoiceActor2","playVoiceActor2",{"voiceId":"23"}]},{"code":657,"indent":0,"parameters":["voiceId = 23"]},{"code":101,"indent":0,"parameters":["Actor0002",0,2,2,""]},{"code":401,"indent":0,"parameters":["あのさ\\."]},{"code":401,"indent":0,"parameters":["ひとつ聞いてもいい？"]},{"code":101,"indent":0,"parameters":["Actor0005",0,0,2]},{"code":401,"indent":0,"parameters":["…？"]},{"code":101,"indent":0,"parameters":["Actor0002",0,2,2,""]},{"code":401,"indent":0,"parameters":["\\N[5]はどうして\\."]},{"code":401,"indent":0,"parameters":["\\N[14]さんを助けたいの？"]},{"code":101,"indent":0,"parameters":["Actor0005",0,0,2]},{"code":401,"indent":0,"parameters":["それは…"]},{"code":230,"indent":0,"parameters":[60]},{"code":357,"indent":0,"parameters":["Plugin_VoiceCommand","playVoiceActor5","playVoiceActor5",{"voiceId":"27"}]},{"code":657,"indent":0,"parameters":["voiceId = 27"]},{"code":101,"indent":0,"parameters":["Actor0005",5,0,2,""]},{"code":401,"indent":0,"parameters":["ボクもよくわからない…"]},{"code":101,"indent":0,"parameters":["Actor0005",5,0,2,""]},{"code":401,"indent":0,"parameters":["でも…\\."]},{"code":401,"indent":0,"parameters":["\\N[14]が言ってたんだ"]},{"code":101,"indent":0,"parameters":["Actor0005",5,0,2]},{"code":401,"indent":0,"parameters":["自分に何ができるんだって"]},{"code":101,"indent":0,"parameters":["Actor0005",5,0,2,""]},{"code":401,"indent":0,"parameters":["学校にも行かないで"]},{"code":101,"indent":0,"parameters":["Actor0005",5,0,2,""]},{"code":401,"indent":0,"parameters":["将来もぼんやりしてて"]},{"code":101,"indent":0,"parameters":["Actor0005",5,0,2,""]},{"code":401,"indent":0,"parameters":["それは 今も変わらないんだけど…"]},{"code":101,"indent":0,"parameters":["Actor0002",5,2,2,""]},{"code":401,"indent":0,"parameters":["…"]},{"code":101,"indent":0,"parameters":["Actor0005",5,0,2]},{"code":401,"indent":0,"parameters":["自分のせいで\\."]},{"code":401,"indent":0,"parameters":["\\N[14]を事件に巻き込んじゃって"]},{"code":101,"indent":0,"parameters":["Actor0005",5,0,2,""]},{"code":401,"indent":0,"parameters":["ボクにもっと力があったなら\\."]},{"code":401,"indent":0,"parameters":["助けられたかもしれないから…"]},{"code":230,"indent":0,"parameters":[30]},{"code":101,"indent":0,"parameters":["Actor0005",5,0,2,""]},{"code":401,"indent":0,"parameters":["独りよがりなのかな\\."]},{"code":101,"indent":0,"parameters":["Actor0005",5,0,2]},{"code":401,"indent":0,"parameters":["魔法が使えるようになって\\."]},{"code":401,"indent":0,"parameters":["少しは強くなれたかなって"]},{"code":101,"indent":0,"parameters":["Actor0005",0,0,2]},{"code":401,"indent":0,"parameters":["誰かの役にたてるかもって\\."]},{"code":401,"indent":0,"parameters":["思ったんだけど…"]},{"code":118,"indent":0,"parameters":["Actor0002"]},{"code":213,"indent":0,"parameters":[-1,1,false]},{"code":357,"indent":0,"parameters":["Plugin_VoiceCommand","playVoiceActor2","playVoiceActor2",{"voiceId":"35"}]},{"code":657,"indent":0,"parameters":["voiceId = 35"]},{"code":101,"indent":0,"parameters":["Actor0002",5,2,2]},{"code":401,"indent":0,"parameters":["そんなことないよ！"]},{"code":213,"indent":0,"parameters":[-1,11,false]},{"code":101,"indent":0,"parameters":["Actor0002",5,2,2]},{"code":401,"indent":0,"parameters":["\\N[5]は…"]},{"code":101,"indent":0,"parameters":["Actor0002",5,2,2]},{"code":401,"indent":0,"parameters":["\\N[14]さんをきっと助けられる！"]},{"code":357,"indent":0,"parameters":["Plugin_VoiceCommand","playVoiceActor2","playVoiceActor2",{"voiceId":"24"}]},{"code":657,"indent":0,"parameters":["voiceId = 24"]},{"code":101,"indent":0,"parameters":["Actor0002",0,2,2]},{"code":401,"indent":0,"parameters":["わたしも協力するから\\."]},{"code":401,"indent":0,"parameters":["ねっ？"]},{"code":357,"indent":0,"parameters":["Plugin_VoiceCommand","playVoiceActor5","playVoiceActor5",{"voiceId":"24"}]},{"code":657,"indent":0,"parameters":["voiceId = 24"]},{"code":101,"indent":0,"parameters":["Actor0005",6,0,2]},{"code":401,"indent":0,"parameters":["えっ…？"]},{"code":101,"indent":0,"parameters":["Actor0005",6,0,2]},{"code":401,"indent":0,"parameters":["お店は？\\."]},{"code":401,"indent":0,"parameters":["孤児院の方だって…"]},{"code":357,"indent":0,"parameters":["Plugin_VoiceCommand","playVoiceActor2","playVoiceActor2",{"voiceId":"26"}]},{"code":657,"indent":0,"parameters":["voiceId = 26"]},{"code":101,"indent":0,"parameters":["Actor0002",6,2,2]},{"code":401,"indent":0,"parameters":["それは！？"]},{"code":230,"indent":0,"parameters":[30]},{"code":213,"indent":0,"parameters":[-1,1,false]},{"code":357,"indent":0,"parameters":["Plugin_VoiceCommand","playVoiceActor2","playVoiceActor2",{"voiceId":"49"}]},{"code":657,"indent":0,"parameters":["voiceId = 49"]},{"code":101,"indent":0,"parameters":["Actor0002",5,2,2]},{"code":401,"indent":0,"parameters":["\\N[5]は気にしなくていいのっ！"]},{"code":213,"indent":0,"parameters":[-1,11,false]},{"code":357,"indent":0,"parameters":["Plugin_VoiceCommand","playVoiceActor5","playVoiceActor5",{"voiceId":"40"}]},{"code":657,"indent":0,"parameters":["voiceId = 40"]},{"code":101,"indent":0,"parameters":["Actor0005",6,0,2,""]},{"code":401,"indent":0,"parameters":["ごめん"]},{"code":357,"indent":0,"parameters":["Plugin_VoiceCommand","playVoiceActor2","playVoiceActor2",{"voiceId":"48"}]},{"code":657,"indent":0,"parameters":["voiceId = 48"]},{"code":101,"indent":0,"parameters":["Actor0002",0,2,2]},{"code":401,"indent":0,"parameters":["んもぅ…"]},{"code":213,"indent":0,"parameters":[-1,8,false]},{"code":230,"indent":0,"parameters":[90]},{"code":213,"indent":0,"parameters":[-1,11,false]},{"code":357,"indent":0,"parameters":["Plugin_VoiceCommand","playVoiceActor2","playVoiceActor2",{"voiceId":"19"}]},{"code":657,"indent":0,"parameters":["voiceId = 19"]},{"code":101,"indent":0,"parameters":["Actor0002",1,2,2,""]},{"code":401,"indent":0,"parameters":["ありがとう \\N[5]\\."]},{"code":401,"indent":0,"parameters":["話してくれて嬉しいよ"]},{"code":213,"indent":0,"parameters":[-1,8,false]},{"code":230,"indent":0,"parameters":[90]},{"code":213,"indent":0,"parameters":[-1,1,false]},{"code":357,"indent":0,"parameters":["Plugin_EventCommand","changeActorFace","changeActorFace",{"faceType":"5"}]},{"code":657,"indent":0,"parameters":["faceType = 5"]},{"code":230,"indent":0,"parameters":[30]},{"code":357,"indent":0,"parameters":["Plugin_VoiceCommand","playVoiceActor2","playVoiceActor2",{"voiceId":"35"}]},{"code":657,"indent":0,"parameters":["voiceId = 35"]},{"code":101,"indent":0,"parameters":["Actor0002",5,2,2,""]},{"code":401,"indent":0,"parameters":["というか！"]},{"code":101,"indent":0,"parameters":["Actor0002",5,2,2,""]},{"code":401,"indent":0,"parameters":["\\N[5]はもっと\\."]},{"code":401,"indent":0,"parameters":["周りを頼った方がいいよ"]},{"code":213,"indent":0,"parameters":[-1,11,false]},{"code":101,"indent":0,"parameters":["Actor0002",0,2,2,""]},{"code":401,"indent":0,"parameters":["まだ子供なんだし"]},{"code":357,"indent":0,"parameters":["Plugin_VoiceCommand","playVoiceActor5","playVoiceActor5",{"voiceId":"21"}]},{"code":657,"indent":0,"parameters":["voiceId = 21"]},{"code":101,"indent":0,"parameters":["Actor0005",5,0,2]},{"code":401,"indent":0,"parameters":["また子供扱い…"]},{"code":213,"indent":0,"parameters":[-1,6,false]},{"code":357,"indent":0,"parameters":["Plugin_VoiceCommand","playVoiceActor2","playVoiceActor2",{"voiceId":"41"}]},{"code":657,"indent":0,"parameters":["voiceId = 41"]},{"code":101,"indent":0,"parameters":["Actor0002",6,2,2,""]},{"code":401,"indent":0,"parameters":["いや…\\."]},{"code":401,"indent":0,"parameters":["そういう事言いたいんじゃなくって"]},{"code":213,"indent":0,"parameters":[-1,8,false]},{"code":230,"indent":0,"parameters":[60]},{"code":213,"indent":0,"parameters":[-1,11,false]},{"code":230,"indent":0,"parameters":[30]},{"code":357,"indent":0,"parameters":["Plugin_VoiceCommand","playVoiceActor2","playVoiceActor2",{"voiceId":"22"}]},{"code":657,"indent":0,"parameters":["voiceId = 22"]},{"code":101,"indent":0,"parameters":["Actor0002",0,2,2]},{"code":401,"indent":0,"parameters":["わたし…\\."]},{"code":401,"indent":0,"parameters":["ほんとうは\\|\\^"]},{"code":101,"indent":0,"parameters":["Actor0043",0,2,2]},{"code":401,"indent":0,"parameters":["話が違うじゃねえか！"]},{"code":230,"indent":0,"parameters":[60]},{"code":242,"indent":0,"parameters":[1]},{"code":230,"indent":0,"parameters":[60]},{"code":213,"indent":0,"parameters":[-1,1,false]},{"code":357,"indent":0,"parameters":["Plugin_VoiceCommand","playVoiceActor2","playVoiceActor2",{"voiceId":"38"}]},{"code":657,"indent":0,"parameters":["voiceId = 38"]},{"code":101,"indent":0,"parameters":["Actor0002",6,2,2,""]},{"code":401,"indent":0,"parameters":["なに！？"]},{"code":213,"indent":0,"parameters":[-1,11,false]},{"code":101,"indent":0,"parameters":["Actor0005",8,0,2,""]},{"code":401,"indent":0,"parameters":["なんだろう…\\."]},{"code":401,"indent":0,"parameters":["向こうの方からだね"]},{"code":118,"indent":0,"parameters":["End"]},{"code":221,"indent":0,"parameters":[]},{"code":242,"indent":0,"parameters":[1]},{"code":357,"indent":0,"parameters":["Plugin_EventCommand","clearPictures","clearPictures",{}]},{"code":222,"indent":0,"parameters":[]},{"code":357,"indent":0,"parameters":["Plugin_EventCommand","exit","exit",{}]},{"code":0,"indent":0,"parameters":[]}],"name":"story_007_060","switchId":1,"trigger":0}