{"id":507,"list":[{"code":111,"indent":0,"parameters":[12,"$gameParty._commonEventNum[\"story_010_map02_001\"] == 1"]},{"code":101,"indent":1,"parameters":["Actor0002",0,2,2,""]},{"code":401,"indent":1,"parameters":["\\N[5]\\. どうしたの？"]},{"code":101,"indent":1,"parameters":["Actor0005",1,0,2,""]},{"code":401,"indent":1,"parameters":["\\N[2]\\."]},{"code":401,"indent":1,"parameters":["ありがとう！"]},{"code":101,"indent":1,"parameters":["Actor0005",1,0,2,""]},{"code":401,"indent":1,"parameters":["ボク\\.みんなに祝ってもらって\\."]},{"code":401,"indent":1,"parameters":["とっても嬉しいよ"]},{"code":118,"indent":1,"parameters":["Actor0002"]},{"code":213,"indent":1,"parameters":[-1,6,false]},{"code":101,"indent":1,"parameters":["Actor0002",6,2,2,""]},{"code":401,"indent":1,"parameters":["えっ！"]},{"code":213,"indent":1,"parameters":[-1,4,false]},{"code":101,"indent":1,"parameters":["Actor0002",6,2,2,""]},{"code":401,"indent":1,"parameters":["あ\\. うん…"]},{"code":213,"indent":1,"parameters":[-1,11,false]},{"code":101,"indent":1,"parameters":["Actor0002",0,2,2,""]},{"code":401,"indent":1,"parameters":["それなら…よかった"]},{"code":101,"indent":1,"parameters":["Actor0002",8,2,2,""]},{"code":401,"indent":1,"parameters":["でも…\\."]},{"code":401,"indent":1,"parameters":["あまり羽目を外したらダメだよ！"]},{"code":101,"indent":1,"parameters":["Actor0005",1,0,2,""]},{"code":401,"indent":1,"parameters":["うん！"]},{"code":0,"indent":1,"parameters":[]},{"code":411,"indent":0,"parameters":[]},{"code":101,"indent":1,"parameters":["Actor0002",0,2,2,""]},{"code":401,"indent":1,"parameters":["\\N[6]さんたち\\."]},{"code":401,"indent":1,"parameters":["遅いなぁ"]},{"code":101,"indent":1,"parameters":["Actor0005",0,0,2,""]},{"code":401,"indent":1,"parameters":["\\N[6]さん\\.たち？"]},{"code":101,"indent":1,"parameters":["Actor0002",0,2,2,""]},{"code":401,"indent":1,"parameters":["うん\\."]},{"code":401,"indent":1,"parameters":["\\N[6]さんの友人も来る予定なんだよ"]},{"code":101,"indent":1,"parameters":["Actor0005",0,0,2,""]},{"code":401,"indent":1,"parameters":["そうだったんだ"]},{"code":0,"indent":1,"parameters":[]},{"code":412,"indent":0,"parameters":[]},{"code":118,"indent":0,"parameters":["End"]},{"code":357,"indent":0,"parameters":["Plugin_EventCommand","exit","exit",{}]},{"code":0,"indent":0,"parameters":[]}],"name":"story_010_map02_001","switchId":1,"trigger":0}