{"id":685,"list":[{"code":111,"indent":0,"parameters":[12,"$gameParty._commonEventNum[\"story_011_map52_002\"] > 1"]},{"code":101,"indent":1,"parameters":["Actor0052",0,2,2,""]},{"code":401,"indent":1,"parameters":["うーん…\\."]},{"code":401,"indent":1,"parameters":["久々に北に来たけど"]},{"code":101,"indent":1,"parameters":["Actor0052",0,2,2,""]},{"code":401,"indent":1,"parameters":["しばれるねぇ…"]},{"code":0,"indent":1,"parameters":[]},{"code":412,"indent":0,"parameters":[]},{"code":111,"indent":0,"parameters":[12,"$gameParty._commonEventNum[\"story_011_map52_002\"] == 1"]},{"code":101,"indent":1,"parameters":["Actor0052",0,2,2,""]},{"code":401,"indent":1,"parameters":["\\N[3]さん…\\."]},{"code":401,"indent":1,"parameters":["少し調子悪そうじゃなかった？"]},{"code":101,"indent":1,"parameters":["Actor0005",0,0,2,""]},{"code":401,"indent":1,"parameters":["えっ…？\\."]},{"code":401,"indent":1,"parameters":["そうでしょうか"]},{"code":101,"indent":1,"parameters":["Actor0052",0,2,2,""]},{"code":401,"indent":1,"parameters":["気のせいなら"]},{"code":401,"indent":1,"parameters":["良いんだけどね"]},{"code":0,"indent":1,"parameters":[]},{"code":412,"indent":0,"parameters":[]},{"code":118,"indent":0,"parameters":["End"]},{"code":357,"indent":0,"parameters":["Plugin_EventCommand","exit","exit",{}]},{"code":0,"indent":0,"parameters":[]}],"name":"story_011_map52_002","switchId":1,"trigger":0}